nobvisual/__init__.py
nobvisual/circlifast.py
nobvisual/cli.py
nobvisual/colorize.py
nobvisual/helpers.py
nobvisual/nob2nstruct.py
nobvisual/nobcompare.py
nobvisual/nobvisual.py
nobvisual/objects.py
nobvisual/tkinter_circlify.py
nobvisual/utils.py
nobvisual-1.0.0.dist-info/LICENSE
nobvisual-1.0.0.dist-info/METADATA
nobvisual-1.0.0.dist-info/WHEEL
nobvisual-1.0.0.dist-info/entry_points.txt
nobvisual-1.0.0.dist-info/top_level.txt
nobvisual-1.0.0.dist-info/RECORD
