Metadata-Version: 2.1
Name: nobvisual
Version: 1.0.0
Summary: Visualization of nested objets.
Home-page: https://gitlab.com/cerfacs/nobvisual
Author: CoopTeam-CERFACS
Author-email: coop@cerfacs.com
Project-URL: Homepage, https://gitlab.com/cerfacs/nobvisual
Project-URL: Documentation, https://nobvisual.readthedocs.io/en/latest/
Project-URL: Bug Tracker, https://gitlab.com/cerfacs/nobvisual/-/issues
Keywords: nested objects,tkinter,circular packing
Classifier: Programming Language :: Python :: 3.7
Classifier: Programming Language :: Python :: 3.8
Classifier: Programming Language :: Python :: 3.9
Classifier: Programming Language :: Python :: 3.10
Classifier: License :: OSI Approved :: MIT License
Requires-Python: >=3.7
Provides-Extra: docs
Provides-Extra: tests
License-File: LICENSE
